pesaflux/__init__.py
pesaflux/client.py
pesaflux-1.0.0.dist-info/licenses/LICENSE
pesaflux-1.0.0.dist-info/METADATA
pesaflux-1.0.0.dist-info/WHEEL
pesaflux-1.0.0.dist-info/top_level.txt
pesaflux-1.0.0.dist-info/RECORD
